numkdoc/__init__.py
numkdoc/numkdoc.py
numkdoc/parser.py
numkdoc/utils.py
Numkdoc-0.4.3.dist-info/LICENSE.txt
Numkdoc-0.4.3.dist-info/METADATA
Numkdoc-0.4.3.dist-info/WHEEL
Numkdoc-0.4.3.dist-info/entry_points.txt
Numkdoc-0.4.3.dist-info/top_level.txt
Numkdoc-0.4.3.dist-info/RECORD
