Metadata-Version: 2.2
Name: Numkdoc
Version: 0.4.3
Summary: Mkdoc plugin to autodoc your numpy docstring
Home-page: https://github.com/napolar/numkdoc
Author: Thomas FEL
Author-email: thomas.fel@protonmail.com
License: MIT
Classifier: Development Status :: 3 - Alpha
Classifier: Intended Audience :: Developers
Classifier: Topic :: Software Development :: Build Tools
Classifier: License :: OSI Approved :: MIT License
Classifier: Programming Language :: Python :: 3.6
License-File: LICENSE.txt
Requires-Dist: mkdocs
Requires-Dist: numpydoc
Dynamic: author
Dynamic: author-email
Dynamic: classifier
Dynamic: description
Dynamic: description-content-type
Dynamic: home-page
Dynamic: license
Dynamic: requires-dist
Dynamic: summary
